MANIFEST.in
README.md
requirements.txt
setup.py
src/sygna_bridge_ivms_util/__init__.py
src/sygna_bridge_ivms_util.egg-info/PKG-INFO
src/sygna_bridge_ivms_util.egg-info/SOURCES.txt
src/sygna_bridge_ivms_util.egg-info/dependency_links.txt
src/sygna_bridge_ivms_util.egg-info/requires.txt
src/sygna_bridge_ivms_util.egg-info/top_level.txt
src/sygna_bridge_ivms_util/generated/__init__.py
src/sygna_bridge_ivms_util/generated/address.py
src/sygna_bridge_ivms_util/generated/address_type_code.py
src/sygna_bridge_ivms_util/generated/beneficiary.py
src/sygna_bridge_ivms_util/generated/beneficiary_vasp.py
src/sygna_bridge_ivms_util/generated/date_and_place_of_birth.py
src/sygna_bridge_ivms_util/generated/identity_payload.py
src/sygna_bridge_ivms_util/generated/intermediary_vasp.py
src/sygna_bridge_ivms_util/generated/legal_person.py
src/sygna_bridge_ivms_util/generated/legal_person_name.py
src/sygna_bridge_ivms_util/generated/legal_person_name_id.py
src/sygna_bridge_ivms_util/generated/legal_person_name_type_code.py
src/sygna_bridge_ivms_util/generated/local_legal_person_name_id.py
src/sygna_bridge_ivms_util/generated/local_natural_person_name_id.py
src/sygna_bridge_ivms_util/generated/national_identification.py
src/sygna_bridge_ivms_util/generated/national_identifier_type_code.py
src/sygna_bridge_ivms_util/generated/natural_person.py
src/sygna_bridge_ivms_util/generated/natural_person_name.py
src/sygna_bridge_ivms_util/generated/natural_person_name_id.py
src/sygna_bridge_ivms_util/generated/natural_person_name_type_code.py
src/sygna_bridge_ivms_util/generated/originating_vasp.py
src/sygna_bridge_ivms_util/generated/originator.py
src/sygna_bridge_ivms_util/generated/payload_metadata.py
src/sygna_bridge_ivms_util/generated/person.py
src/sygna_bridge_ivms_util/generated/transliteration_method_code.py