Metadata-Version: 2.1
Name: sygna-bridge-ivms-util
Version: 0.0.6
Summary: This is a Python library for building IVMS data structure.
Home-page: https://github.com/CoolBitX-Technology/sygna-bridge-ivms-utils
Author: frank.chen
Author-email: frank.chen@coolbitx.com
License: MIT
Keywords: sygna-bridge-util sygna bridge sygna-bridge ecosystem ivms
Platform: UNKNOWN
Requires-Python: >=3.7
